iamcore/irn/__init__.py
iamcore/irn/const.py
iamcore/irn/exceptions.py
iamcore/irn/irn.py
iamcore/irn/utils.py
iamcore_irn_py-0.0.1.dist-info/METADATA
iamcore_irn_py-0.0.1.dist-info/WHEEL
iamcore_irn_py-0.0.1.dist-info/top_level.txt
iamcore_irn_py-0.0.1.dist-info/RECORD
